vbpaper/__init__.py
vbpaper/__main__.py
vbpaper/answer.py
vbpaper/functions.py
vbpaper/main.py
vbpaper/normalize.py
vbpaper/rename.py
vbpaper/render.py
vbpaper/resize.py
vbpaper/start.py
vbpaper-0.1.27.dist-info/METADATA
vbpaper-0.1.27.dist-info/WHEEL
vbpaper-0.1.27.dist-info/entry_points.txt
vbpaper-0.1.27.dist-info/RECORD
