Metadata-Version: 2.1
Name: vbpaper
Version: 0.1.27
Summary: Added support for twocolumn and onecolumn documents
Author: vaibhavblayer
Author-email: vaibhavblayer@gmail.com
Requires-Python: >=3.11,<4.0
Classifier: Programming Language :: Python :: 3
Classifier: Programming Language :: Python :: 3.11
